shipyard_smartsheets/__init__.py
shipyard_smartsheets/cli/__init__.py
shipyard_smartsheets/cli/authtest.py
shipyard_smartsheets/cli/download.py
shipyard_smartsheets/cli/upload.py
shipyard_smartsheets/smartsheets.py
shipyard_smartsheets-0.1.1.dist-info/METADATA
shipyard_smartsheets-0.1.1.dist-info/WHEEL
shipyard_smartsheets-0.1.1.dist-info/RECORD
