Metadata-Version: 2.1
Name: shipyard-smartsheets
Version: 0.1.1
Summary: 
Author: wrp801
Author-email: wespoulsen@gmail.com
Requires-Python: >=3.9,<4.0
Classifier: Programming Language :: Python :: 3
Classifier: Programming Language :: Python :: 3.9
Classifier: Programming Language :: Python :: 3.10
Classifier: Programming Language :: Python :: 3.11
Requires-Dist: openpyxl (>=3.1.2,<4.0.0)
Requires-Dist: pandas (>=2.0,<3.0)
Requires-Dist: requests (==2.31)
Requires-Dist: shipyard-bp-utils (>=1.2.1,<2.0.0)
Requires-Dist: shipyard-templates (>=0.8.2,<0.9.0)
Requires-Dist: smartsheet-python-sdk (>=3.0.2,<4.0.0)
